[
    {
        "model": "auth.group",
        "pk": 1,
        "fields": {
            "name": "Admin"
        }
    },
    {
        "model": "roles.roles",
        "pk": 1,
        "fields": {
            "name": "Admin",
            "permissions": []
        }
    },
    {
        "model": "auth.group_permissions",
        "pk": 1,
        "fields": {
            "group_id": 1,
            "permission_id": 1
        }
    },
    {
        "model": "auth.group_permissions",
        "pk": 2,
        "fields": {
            "group_id": 1,
            "permission_id": 2
        }
    },
    {
        "model": "auth.group_permissions",
        "pk": 3,
        "fields": {
            "group_id": 1,
            "permission_id": 3
        }
    },
    {
        "model": "auth.group_permissions",
        "pk": 4,
        "fields": {
            "group_id": 1,
            "permission_id": 4
        }
    },
    {
        "model": "auth.group_permissions",
        "pk": 5,
        "fields": {
            "group_id": 1,
            "permission_id": 5
        }
    },
    {
        "model": "auth.group_permissions",
        "pk": 6,
        "fields": {
            "group_id": 1,
            "permission_id": 6
        }
    },
    {
        "model": "auth.group_permissions",
        "pk": 7,
        "fields": {
            "group_id": 1,
            "permission_id": 7
        }
    },
    {
        "model": "auth.group_permissions",
        "pk": 8,
        "fields": {
            "group_id": 1,
            "permission_id": 8
        }
    },
    {
        "model": "auth.group_permissions",
        "pk": 9,
        "fields": {
            "group_id": 1,
            "permission_id": 9
        }
    },
    {
        "model": "auth.group_permissions",
        "pk": 10,
        "fields": {
            "group_id": 1,
            "permission_id": 10
        }
    },
    {
        "model": "auth.group_permissions",
        "pk": 11,
        "fields": {
            "group_id": 1,
            "permission_id": 11
        }
    },
    {
        "model": "auth.group_permissions",
        "pk": 12,
        "fields": {
            "group_id": 1,
            "permission_id": 12
        }
    },
    {
        "model": "auth.group_permissions",
        "pk": 13,
        "fields": {
            "group_id": 1,
            "permission_id": 13
        }
    },
    {
        "model": "auth.group_permissions",
        "pk": 14,
        "fields": {
            "group_id": 1,
            "permission_id": 14
        }
    },
    {
        "model": "auth.group_permissions",
        "pk": 15,
        "fields": {
            "group_id": 1,
            "permission_id": 15
        }
    },
    {
        "model": "auth.group_permissions",
        "pk": 16,
        "fields": {
            "group_id": 1,
            "permission_id": 16
        }
    },
    {
        "model": "auth.group_permissions",
        "pk": 17,
        "fields": {
            "group_id": 1,
            "permission_id": 17
        }
    },
    {
        "model": "auth.group_permissions",
        "pk": 18,
        "fields": {
            "group_id": 1,
            "permission_id": 18
        }
    },
    {
        "model": "auth.group_permissions",
        "pk": 19,
        "fields": {
            "group_id": 1,
            "permission_id": 19
        }
    },
    {
        "model": "auth.group_permissions",
        "pk": 20,
        "fields": {
            "group_id": 1,
            "permission_id": 20
        }
    },
    {
        "model": "auth.group_permissions",
        "pk": 21,
        "fields": {
            "group_id": 1,
            "permission_id": 21
        }
    },
    {
        "model": "auth.group_permissions",
        "pk": 22,
        "fields": {
            "group_id": 1,
            "permission_id": 22
        }
    },
    {
        "model": "auth.group_permissions",
        "pk": 23,
        "fields": {
            "group_id": 1,
            "permission_id": 23
        }
    },
    {
        "model": "auth.group_permissions",
        "pk": 24,
        "fields": {
            "group_id": 1,
            "permission_id": 24
        }
    },
    {
        "model": "auth.group_permissions",
        "pk": 25,
        "fields": {
            "group_id": 1,
            "permission_id": 25
        }
    },
    {
        "model": "auth.group_permissions",
        "pk": 26,
        "fields": {
            "group_id": 1,
            "permission_id": 26
        }
    },
    {
        "model": "auth.group_permissions",
        "pk": 27,
        "fields": {
            "group_id": 1,
            "permission_id": 27
        }
    },
    {
        "model": "auth.group_permissions",
        "pk": 28,
        "fields": {
            "group_id": 1,
            "permission_id": 28
        }
    },
    {
        "model": "auth.group_permissions",
        "pk": 29,
        "fields": {
            "group_id": 1,
            "permission_id": 29
        }
    },
    {
        "model": "auth.group_permissions",
        "pk": 30,
        "fields": {
            "group_id": 1,
            "permission_id": 30
        }
    },
    {
        "model": "auth.group_permissions",
        "pk": 31,
        "fields": {
            "group_id": 1,
            "permission_id": 31
        }
    },
    {
        "model": "auth.group_permissions",
        "pk": 32,
        "fields": {
            "group_id": 1,
            "permission_id": 32
        }
    },
    {
        "model": "auth.group_permissions",
        "pk": 33,
        "fields": {
            "group_id": 1,
            "permission_id": 33
        }
    },
    {
        "model": "auth.group_permissions",
        "pk": 35,
        "fields": {
            "group_id": 1,
            "permission_id": 35
        }
    },
    {
        "model": "auth.group_permissions",
        "pk": 36,
        "fields": {
            "group_id": 1,
            "permission_id": 36
        }
    },
    {
        "model": "auth.group_permissions",
        "pk": 37,
        "fields": {
            "group_id": 1,
            "permission_id": 37
        }
    },
    {
        "model": "auth.group_permissions",
        "pk": 38,
        "fields": {
            "group_id": 1,
            "permission_id": 38
        }
    },
    {
        "model": "auth.group_permissions",
        "pk": 39,
        "fields": {
            "group_id": 1,
            "permission_id": 39
        }
    },
    {
        "model": "auth.group_permissions",
        "pk": 40,
        "fields": {
            "group_id": 1,
            "permission_id": 40
        }
    },    
    {
        "model": "auth.group_permissions",
        "pk": 41,
        "fields": {
            "group_id": 1,
            "permission_id": 41
        }
    },    
    {
        "model": "auth.group_permissions",
        "pk": 42,
        "fields": {
            "group_id": 1,
            "permission_id": 42
        }
    },    
    {
        "model": "auth.group_permissions",
        "pk": 43,
        "fields": {
            "group_id": 1,
            "permission_id": 43
        }
    },    
    {
        "model": "auth.group_permissions",
        "pk": 44,
        "fields": {
            "group_id": 1,
            "permission_id": 44
        }
    },    
    {
        "model": "auth.group_permissions",
        "pk": 45,
        "fields": {
            "group_id": 1,
            "permission_id": 45
        }
    },    
    {
        "model": "auth.group_permissions",
        "pk": 46,
        "fields": {
            "group_id": 1,
            "permission_id": 46
        }
    },    
    {
        "model": "auth.group_permissions",
        "pk": 46,
        "fields": {
            "group_id": 1,
            "permission_id": 46
        }
    },    
    {
        "model": "auth.group_permissions",
        "pk": 47,
        "fields": {
            "group_id": 1,
            "permission_id": 47
        }
    },    
    {
        "model": "auth.group_permissions",
        "pk": 48,
        "fields": {
            "group_id": 1,
            "permission_id": 48
        }
    },    
    {
        "model": "auth.group_permissions",
        "pk": 49,
        "fields": {
            "group_id": 1,
            "permission_id": 49
        }
    },    
    {
        "model": "auth.group_permissions",
        "pk": 50,
        "fields": {
            "group_id": 1,
            "permission_id": 50
        }
    },    
    {
        "model": "auth.group_permissions",
        "pk": 51,
        "fields": {
            "group_id": 1,
            "permission_id": 51
        }
    },    
    {
        "model": "auth.group_permissions",
        "pk": 52,
        "fields": {
            "group_id": 1,
            "permission_id": 52
        }
    },    
    {
        "model": "auth.group_permissions",
        "pk": 53,
        "fields": {
            "group_id": 1,
            "permission_id": 53
        }
    },    
    {
        "model": "auth.group_permissions",
        "pk": 54,
        "fields": {
            "group_id": 1,
            "permission_id": 54
        }
    },    
    {
        "model": "auth.group_permissions",
        "pk": 55,
        "fields": {
            "group_id": 1,
            "permission_id": 55
        }
    },    
    {
        "model": "auth.group_permissions",
        "pk": 56,
        "fields": {
            "group_id": 1,
            "permission_id": 56
        }
    },    
    {
        "model": "auth.group_permissions",
        "pk": 57,
        "fields": {
            "group_id": 1,
            "permission_id": 57
        }
    },    
    {
        "model": "auth.group_permissions",
        "pk": 58,
        "fields": {
            "group_id": 1,
            "permission_id": 58
        }
    },    
    {
        "model": "auth.group_permissions",
        "pk": 59,
        "fields": {
            "group_id": 1,
            "permission_id": 59
        }
    },    
    {
        "model": "auth.group_permissions",
        "pk": 60,
        "fields": {
            "group_id": 1,
            "permission_id": 60
        }
    },    
    {
        "model": "auth.group_permissions",
        "pk": 61,
        "fields": {
            "group_id": 1,
            "permission_id": 61
        }
    },    
    {
        "model": "auth.group_permissions",
        "pk": 62,
        "fields": {
            "group_id": 1,
            "permission_id": 62
        }
    },    
    {
        "model": "auth.group_permissions",
        "pk": 63,
        "fields": {
            "group_id": 1,
            "permission_id": 63
        }
    },    
    {
        "model": "auth.group_permissions",
        "pk": 64,
        "fields": {
            "group_id": 1,
            "permission_id": 64
        }
    },    
    {
        "model": "auth.group_permissions",
        "pk": 65,
        "fields": {
            "group_id": 1,
            "permission_id": 65
        }
    },    
    {
        "model": "auth.group_permissions",
        "pk": 66,
        "fields": {
            "group_id": 1,
            "permission_id": 66
        }
    },    
    {
        "model": "auth.group_permissions",
        "pk": 67,
        "fields": {
            "group_id": 1,
            "permission_id": 67
        }
    },    
    {
        "model": "auth.group_permissions",
        "pk": 68,
        "fields": {
            "group_id": 1,
            "permission_id": 68
        }
    },    
    {
        "model": "auth.group_permissions",
        "pk": 69,
        "fields": {
            "group_id": 1,
            "permission_id": 69
        }
    },    
    {
        "model": "auth.group_permissions",
        "pk": 70,
        "fields": {
            "group_id": 1,
            "permission_id": 70
        }
    },    
    {
        "model": "auth.group_permissions",
        "pk": 71,
        "fields": {
            "group_id": 1,
            "permission_id": 71
        }
    },    
    {
        "model": "auth.group_permissions",
        "pk": 72,
        "fields": {
            "group_id": 1,
            "permission_id": 72
        }
    },    
    {
        "model": "auth.group_permissions",
        "pk": 73,
        "fields": {
            "group_id": 1,
            "permission_id": 73
        }
    },    
    {
        "model": "auth.group_permissions",
        "pk": 74,
        "fields": {
            "group_id": 1,
            "permission_id": 74
        }
    },    
    {
        "model": "auth.group_permissions",
        "pk": 75,
        "fields": {
            "group_id": 1,
            "permission_id": 75
        }
    },    
    {
        "model": "auth.group_permissions",
        "pk": 76,
        "fields": {
            "group_id": 1,
            "permission_id": 76
        }
    },    
    {
        "model": "auth.group_permissions",
        "pk": 77,
        "fields": {
            "group_id": 1,
            "permission_id": 77
        }
    },    
    {
        "model": "auth.group_permissions",
        "pk": 78,
        "fields": {
            "group_id": 1,
            "permission_id": 78
        }
    },    
    {
        "model": "auth.group_permissions",
        "pk": 79,
        "fields": {
            "group_id": 1,
            "permission_id": 79
        }
    },    
    {
        "model": "auth.group_permissions",
        "pk": 80,
        "fields": {
            "group_id": 1,
            "permission_id": 80
        }
    },    
    {
        "model": "auth.group_permissions",
        "pk": 81,
        "fields": {
            "group_id": 1,
            "permission_id": 81
        }
    },    
    {
        "model": "auth.group_permissions",
        "pk": 82,
        "fields": {
            "group_id": 1,
            "permission_id": 82
        }
    },    
    {
        "model": "auth.group_permissions",
        "pk": 83,
        "fields": {
            "group_id": 1,
            "permission_id": 83
        }
    },    
    {
        "model": "auth.group_permissions",
        "pk": 84,
        "fields": {
            "group_id": 1,
            "permission_id": 84
        }
    },    
    {
        "model": "auth.group_permissions",
        "pk": 85,
        "fields": {
            "group_id": 1,
            "permission_id": 85
        }
    },    
    {
        "model": "auth.group_permissions",
        "pk": 86,
        "fields": {
            "group_id": 1,
            "permission_id": 86
        }
    },    
    {
        "model": "auth.group_permissions",
        "pk": 87,
        "fields": {
            "group_id": 1,
            "permission_id": 87
        }
    },    
    {
        "model": "auth.group_permissions",
        "pk": 88,
        "fields": {
            "group_id": 1,
            "permission_id": 88
        }
    },    
    {
        "model": "auth.group_permissions",
        "pk": 89,
        "fields": {
            "group_id": 1,
            "permission_id": 89
        }
    },    
    {
        "model": "auth.group_permissions",
        "pk": 90,
        "fields": {
            "group_id": 1,
            "permission_id": 90
        }
    },    
    {
        "model": "auth.group_permissions",
        "pk": 91,
        "fields": {
            "group_id": 1,
            "permission_id": 91
        }
    },    
    {
        "model": "auth.group_permissions",
        "pk": 92,
        "fields": {
            "group_id": 1,
            "permission_id": 92
        }
    },    
    {
        "model": "auth.group_permissions",
        "pk": 93,
        "fields": {
            "group_id": 1,
            "permission_id": 93
        }
    },    
    {
        "model": "auth.group_permissions",
        "pk": 94,
        "fields": {
            "group_id": 1,
            "permission_id": 94
        }
    },    
    {
        "model": "auth.group_permissions",
        "pk": 95,
        "fields": {
            "group_id": 1,
            "permission_id": 95
        }
    },    
    {
        "model": "auth.group_permissions",
        "pk": 96,
        "fields": {
            "group_id": 1,
            "permission_id": 96
        }
    },    
    {
        "model": "auth.group_permissions",
        "pk": 97,
        "fields": {
            "group_id": 1,
            "permission_id": 97
        }
    },    
    {
        "model": "auth.group_permissions",
        "pk": 98,
        "fields": {
            "group_id": 1,
            "permission_id": 98
        }
    },    
    {
        "model": "auth.group_permissions",
        "pk": 99,
        "fields": {
            "group_id": 1,
            "permission_id": 99
        }
    },    
    {
        "model": "auth.group_permissions",
        "pk": 100,
        "fields": {
            "group_id": 1,
            "permission_id": 100
        }
    },    
    {
        "model": "auth.group_permissions",
        "pk": 101,
        "fields": {
            "group_id": 1,
            "permission_id": 101
        }
    },    
    {
        "model": "auth.group_permissions",
        "pk": 102,
        "fields": {
            "group_id": 1,
            "permission_id": 102
        }
    },    
    {
        "model": "auth.group_permissions",
        "pk": 103,
        "fields": {
            "group_id": 1,
            "permission_id": 103
        }
    },    
    {
        "model": "auth.group_permissions",
        "pk": 104,
        "fields": {
            "group_id": 1,
            "permission_id": 104
        }
    },    
    {
        "model": "auth.group_permissions",
        "pk": 105,
        "fields": {
            "group_id": 1,
            "permission_id": 105
        }
    },    
    {
        "model": "auth.group_permissions",
        "pk": 106,
        "fields": {
            "group_id": 1,
            "permission_id": 106
        }
    },    
    {
        "model": "auth.group_permissions",
        "pk": 107,
        "fields": {
            "group_id": 1,
            "permission_id": 107
        }
    },    
    {
        "model": "auth.group_permissions",
        "pk": 108,
        "fields": {
            "group_id": 1,
            "permission_id": 108
        }
    },    
    {
        "model": "auth.group_permissions",
        "pk": 109,
        "fields": {
            "group_id": 1,
            "permission_id": 109
        }
    },    
    {
        "model": "auth.group_permissions",
        "pk": 110,
        "fields": {
            "group_id": 1,
            "permission_id": 110
        }
    },    
    {
        "model": "auth.group_permissions",
        "pk": 111,
        "fields": {
            "group_id": 1,
            "permission_id": 111
        }
    },    
    {
        "model": "auth.group_permissions",
        "pk": 112,
        "fields": {
            "group_id": 1,
            "permission_id": 112
        }
    },    
    {
        "model": "users.user",
        "pk": 1,
        "fields": {
            "username": "admin",
            "password": "pbkdf2_sha256$720000$Sv9Q4AJC9RSsldpfb2QTkI$p9/YKqXkcyDh+P1mscc3vamNnSnbrw72V9sKixudsaI=",
            "email": "admin@test.com",
            "groups": [
                1
            ],
            "is_active": 1
        }
    }
]